hyc_mcp_demo2/__init__.py
hyc_mcp_demo2-0.1.0.dist-info/WHEEL
hyc_mcp_demo2-0.1.0.dist-info/entry_points.txt
hyc_mcp_demo2-0.1.0.dist-info/METADATA
hyc_mcp_demo2-0.1.0.dist-info/RECORD
