Metadata-Version: 2.3
Name: hyc-mcp-demo2
Version: 0.1.0
Summary: Add your description here
Requires-Dist: mcp[cli]>=1.12.2
Requires-Python: >=3.12.6
